{
"name":"root","size":"245","children": [{
"name":"82387","size":"1"},{
"name":"rep178877","size":"21","children": [{
"name":"18256","size":"1"},{
"name":"18609","size":"1"},{
"name":"18321","size":"1"},{
"name":"178860","size":"1"},{
"name":"18676","size":"1"},{
"name":"178862","size":"1"},{
"name":"178858","size":"1"},{
"name":"178863","size":"1"},{
"name":"18350","size":"1"},{
"name":"178877","size":"1"},{
"name":"178878","size":"1"},{
"name":"178859","size":"1"},{
"name":"18261","size":"1"},{
"name":"178861","size":"1"},{
"name":"18412","size":"1"},{
"name":"18253","size":"1"},{
"name":"18293","size":"1"},{
"name":"165412","size":"1"},{
"name":"242627","size":"1"},{
"name":"178864","size":"1"},{
"name":"18266","size":"1"}]
},{
"name":"rep179290","size":"21","children": [{
"name":"179553","size":"1"},{
"name":"179639","size":"1"},{
"name":"179591","size":"1"},{
"name":"179590","size":"1"},{
"name":"179589","size":"1"},{
"name":"179452","size":"1"},{
"name":"102208","size":"1"},{
"name":"179449","size":"1"},{
"name":"179294","size":"1"},{
"name":"179588","size":"1"},{
"name":"179451","size":"1"},{
"name":"179450","size":"1"},{
"name":"179638","size":"1"},{
"name":"10527","size":"1"},{
"name":"179592","size":"1"},{
"name":"179640","size":"1"},{
"name":"179552","size":"1"},{
"name":"179593","size":"1"},{
"name":"179290","size":"1"},{
"name":"179587","size":"1"},{
"name":"179292","size":"1"}]
},{
"name":"57171","size":"1"},{
"name":"rep20992","size":"52","children": [{
"name":"255529","size":"1"},{
"name":"243622","size":"1"},{
"name":"81172","size":"1"},{
"name":"253318","size":"1"},{
"name":"246518","size":"1"},{
"name":"1590","size":"1"},{
"name":"241660","size":"1"},{
"name":"247561","size":"1"},{
"name":"242572","size":"1"},{
"name":"247027","size":"1"},{
"name":"231575","size":"1"},{
"name":"253333","size":"1"},{
"name":"247946","size":"1"},{
"name":"234696","size":"1"},{
"name":"214727","size":"1"},{
"name":"100683","size":"1"},{
"name":"232543","size":"1"},{
"name":"214899","size":"1"},{
"name":"248921","size":"1"},{
"name":"231574","size":"1"},{
"name":"1631","size":"1"},{
"name":"255530","size":"1"},{
"name":"288","size":"1"},{
"name":"20992","size":"1"},{
"name":"243623","size":"1"},{
"name":"244001","size":"1"},{
"name":"247192","size":"1"},{
"name":"249413","size":"1"},{
"name":"255533","size":"1"},{
"name":"230607","size":"1"},{
"name":"255531","size":"1"},{
"name":"255532","size":"1"},{
"name":"214825","size":"1"},{
"name":"253705","size":"1"},{
"name":"244002","size":"1"},{
"name":"235862","size":"1"},{
"name":"242576","size":"1"},{
"name":"244931","size":"1"},{
"name":"254412","size":"1"},{
"name":"235873","size":"1"},{
"name":"232542","size":"1"},{
"name":"248920","size":"1"},{
"name":"255536","size":"1"},{
"name":"214752","size":"1"},{
"name":"242324","size":"1"},{
"name":"255534","size":"1"},{
"name":"253706","size":"1"},{
"name":"322","size":"1"},{
"name":"141523","size":"1"},{
"name":"233554","size":"1"},{
"name":"232498","size":"1"},{
"name":"254413","size":"1"}]
},{
"name":"rep69335","size":"20","children": [{
"name":"69335","size":"1"},{
"name":"69328","size":"1"},{
"name":"69332","size":"1"},{
"name":"69338","size":"1"},{
"name":"69337","size":"1"},{
"name":"69343","size":"1"},{
"name":"69339","size":"1"},{
"name":"69327","size":"1"},{
"name":"69336","size":"1"},{
"name":"69333","size":"1"},{
"name":"69344","size":"1"},{
"name":"69330","size":"1"},{
"name":"69334","size":"1"},{
"name":"69325","size":"1"},{
"name":"69329","size":"1"},{
"name":"69341","size":"1"},{
"name":"69342","size":"1"},{
"name":"69326","size":"1"},{
"name":"69340","size":"1"},{
"name":"69331","size":"1"}]
},{
"name":"rep38814","size":"21","children": [{
"name":"80128","size":"1"},{
"name":"80124","size":"1"},{
"name":"28505","size":"1"},{
"name":"38816","size":"1"},{
"name":"116356","size":"1"},{
"name":"38813","size":"1"},{
"name":"38817","size":"1"},{
"name":"80122","size":"1"},{
"name":"38812","size":"1"},{
"name":"38815","size":"1"},{
"name":"38814","size":"1"},{
"name":"38820","size":"1"},{
"name":"38818","size":"1"},{
"name":"38819","size":"1"},{
"name":"80126","size":"1"},{
"name":"38801","size":"1"},{
"name":"80125","size":"1"},{
"name":"80123","size":"1"},{
"name":"80127","size":"1"},{
"name":"80129","size":"1"},{
"name":"38821","size":"1"}]
},{
"name":"155650","size":"1"},{
"name":"179666","size":"1"},{
"name":"rep195948","size":"21","children": [{
"name":"195946","size":"1"},{
"name":"195908","size":"1"},{
"name":"30702","size":"1"},{
"name":"20665","size":"1"},{
"name":"30700","size":"1"},{
"name":"252482","size":"1"},{
"name":"30705","size":"1"},{
"name":"195948","size":"1"},{
"name":"195943","size":"1"},{
"name":"238938","size":"1"},{
"name":"195942","size":"1"},{
"name":"30706","size":"1"},{
"name":"238940","size":"1"},{
"name":"195945","size":"1"},{
"name":"8839","size":"1"},{
"name":"30703","size":"1"},{
"name":"195944","size":"1"},{
"name":"30701","size":"1"},{
"name":"7377","size":"1"},{
"name":"238939","size":"1"},{
"name":"30704","size":"1"}]
},{
"name":"125635","size":"1"},{
"name":"rep155722","size":"20","children": [{
"name":"89559","size":"1"},{
"name":"5097","size":"1"},{
"name":"67076","size":"1"},{
"name":"153143","size":"1"},{
"name":"89192","size":"1"},{
"name":"105760","size":"1"},{
"name":"89038","size":"1"},{
"name":"6254","size":"1"},{
"name":"155722","size":"1"},{
"name":"89253","size":"1"},{
"name":"101448","size":"1"},{
"name":"97069","size":"1"},{
"name":"97338","size":"1"},{
"name":"153081","size":"1"},{
"name":"98605","size":"1"},{
"name":"97480","size":"1"},{
"name":"173059","size":"1"},{
"name":"98090","size":"1"},{
"name":"97363","size":"1"},{
"name":"97932","size":"1"}]
},{
"name":"rep85441","size":"23","children": [{
"name":"86020","size":"1"},{
"name":"85438","size":"1"},{
"name":"86025","size":"1"},{
"name":"85440","size":"1"},{
"name":"86029","size":"1"},{
"name":"86021","size":"1"},{
"name":"87109","size":"1"},{
"name":"86024","size":"1"},{
"name":"87107","size":"1"},{
"name":"85439","size":"1"},{
"name":"86028","size":"1"},{
"name":"86030","size":"1"},{
"name":"85441","size":"1"},{
"name":"24166","size":"1"},{
"name":"87108","size":"1"},{
"name":"86022","size":"1"},{
"name":"87111","size":"1"},{
"name":"86027","size":"1"},{
"name":"86023","size":"1"},{
"name":"87110","size":"1"},{
"name":"87127","size":"1"},{
"name":"86026","size":"1"},{
"name":"85442","size":"1"}]
},{
"name":"rep102376","size":"21","children": [{
"name":"1318","size":"1"},{
"name":"39966","size":"1"},{
"name":"151672","size":"1"},{
"name":"5836","size":"1"},{
"name":"102376","size":"1"},{
"name":"151671","size":"1"},{
"name":"151666","size":"1"},{
"name":"151674","size":"1"},{
"name":"151665","size":"1"},{
"name":"12","size":"1"},{
"name":"151673","size":"1"},{
"name":"151667","size":"1"},{
"name":"48883","size":"1"},{
"name":"151669","size":"1"},{
"name":"151670","size":"1"},{
"name":"695","size":"1"},{
"name":"117940","size":"1"},{
"name":"151668","size":"1"},{
"name":"27","size":"1"},{
"name":"33042","size":"1"},{
"name":"1316","size":"1"}]
},{
"name":"rep240620","size":"20","children": [{
"name":"241139","size":"1"},{
"name":"235623","size":"1"},{
"name":"240751","size":"1"},{
"name":"241124","size":"1"},{
"name":"240672","size":"1"},{
"name":"240606","size":"1"},{
"name":"240668","size":"1"},{
"name":"240695","size":"1"},{
"name":"240764","size":"1"},{
"name":"241123","size":"1"},{
"name":"240755","size":"1"},{
"name":"240905","size":"1"},{
"name":"240670","size":"1"},{
"name":"240537","size":"1"},{
"name":"240669","size":"1"},{
"name":"241289","size":"1"},{
"name":"240619","size":"1"},{
"name":"241148","size":"1"},{
"name":"240906","size":"1"},{
"name":"240620","size":"1"}]
}]
}