{
"name":"root","children": [{
"name":"one","children": [{
"name":"eleven","children": [{
"name":"thirtyone"},{
"name":"thirtytwo"}]
},{
"name":"twelve"}]
},{
"name":"two","children": [{
"name":"thirteen"},{
"name":"fourteen"}]
},{
"name":"three","children": [{
"name":"fifteen"},{
"name":"sixteen","children": [{
"name":"thirtythree"}]
}]
},{
"name":"four","children": [{
"name":"seventeen"},{
"name":"eighteen"}]
},{
"name":"five","children": [{
"name":"ninteen","children": [{
"name":"thirtyfour"}]
},{
"name":"twenty"}]
},{
"name":"six","children": [{
"name":"twentyone"},{
"name":"twentytwo"}]
},{
"name":"seven","children": [{
"name":"twentythree"},{
"name":"twentyfour"}]
},{
"name":"eight","children": [{
"name":"twentyfive"},{
"name":"twentysix"}]
},{
"name":"nine","children": [{
"name":"twentyseven"},{
"name":"twentyeight"}]
},{
"name":"ten","children": [{
"name":"twentynine","children": [{
"name":"thirtyfive","children": [{
"name":"thirtyseven"}]
},{
"name":"thirtysix"}]
},{
"name":"thirty"}]
}]
}